{
  "version": "6",
  "dialect": "sqlite",
  "id": "17bbc005-d59a-4c94-80e5-30347d66d554",
  "prevId": "00000000-0000-0000-0000-000000000000",
  "tables": {
    "key_post": {
      "name": "key_post",
      "columns": {
        "id": {
          "name": "id",
          "type": "integer",
          "primaryKey": true,
          "notNull": true,
          "autoincrement": true
        },
        "name": {
          "name": "name",
          "type": "text(256)",
          "primaryKey": false,
          "notNull": false,
          "autoincrement": false
        },
        "created_at": {
          "name": "created_at",
          "type": "integer",
          "primaryKey": false,
          "notNull": true,
          "autoincrement": false,
          "default": "CURRENT_TIMESTAMP"
        },
        "updatedAt": {
          "name": "updatedAt",
          "type": "integer",
          "primaryKey": false,
          "notNull": false,
          "autoincrement": false
        }
      },
      "indexes": {
        "name_idx": {
          "name": "name_idx",
          "columns": [
            "name"
          ],
          "isUnique": false
        }
      },
      "foreignKeys": {},
      "compositePrimaryKeys": {},
      "uniqueConstraints": {}
    }
  },
  "enums": {},
  "_meta": {
    "schemas": {},
    "tables": {},
    "columns": {}
  }
}